{
  "id": 1412,
  "title": "Amputation | Limb Loss | MedlinePlus",
  "content": "Limb Loss On this page Basics Summary Start Here Prevention and Risk Factors Treatments and Therapies Learn More Living With Related Issues Specifics See, Play and Learn No links available Research Clinical Trials Journal Articles Resources No links available For You Children Patient Handouts Summary People can lose all or part of an arm or leg for many reasons. Common ones include: Problems with the flow of blood through your body. These may be the result of atherosclerosis or diabetes. Severe cases may result in amputation (the surgical removal of a limb). Injuries, including from traffic accidents and military combat. Cancer. Birth defects. Some amputees have phantom pain, which is the feeling of pain in the missing limb. Other physical problems include surgical complications and skin problems if you wear an artificial limb . Many amputees use an artificial limb. Learning how to use it takes time. Physical therapy can help you adapt. Recovery from the loss of a limb can be hard. Sadness, anger, and frustration are common. If you are having a tough time, talk to your health care provider. Treatment with medicine or counseling can help. Start Here First Step -- A Guide for Adapting to Limb Loss (Amputee Coalition) - PDF Points to Know and Consider When Preparing for and Undergoing an Amputation (Amputee Coalition) Prevention and Risk Factors Amputations (Occupational Safety and Health Administration) - PDF Diabetic Complications and Amputation Prevention (American College of Foot and Ankle Surgeons) Also in Spanish Treatments and Therapies Care of Your Wounds After Amputation Surgery (Amputee Coalition) Living With Beginning Your New Journey: Below Knee Amputation (Amputee Coalition) Beginning Your New Journey: Upper-Limb Amputation Behginning Your New Journey: Above Knee Amputation Emotional Recovery (Amputee Coalition) Rehabilitation after Limb Amputation (Merck & Co., Inc.) Also in Spanish When a Parent Loses a Limb: Helping Children Cope (Amputee Coalition) Related Issues Residual Limb Pain (Mayo Foundation for Medical Education and Research) Wound Care: Preventing Infection (Amputee Coalition) Specifics Before Your Amputation: Questions to Ask Your Surgeon (Amputee Coalition) Living with Phantom Limb Pain (Amputee Coalition) Clinical Trials ClinicalTrials.gov: Amputation (National Institutes of Health) ClinicalTrials.gov: Amputation, Traumatic (National Institutes of Health) ClinicalTrials.gov: Amputees (National Institutes of Health) ClinicalTrials.gov: Artificial Limbs (National Institutes of Health) ClinicalTrials.gov: Phantom Limb (National Institutes of Health) Journal Articles References and abstracts from MEDLINE/PubMed (National Library of Medicine) Article: Physical and sports rehabilitation of patients with amputations using adaptive badminton. Article: Augmented reality for advanced prosthetic training in non-amputees. Article: Non-infectious skeletal complications in the lower extremity after treatment with a... Limb Loss -- see more articles Children Missing or Incompletely Formed Limbs (Merck & Co., Inc.) Also in Spanish Pediatric Limb Loss and Limb Difference: An Introduction for Parents (Amputee Coalition) Patient Handouts Foot amputation - discharge (Medical Encyclopedia) Also in Spanish Leg amputation - discharge (Medical Encyclopedia) Also in Spanish Leg or foot amputation (Medical Encyclopedia) Also in Spanish Leg or foot amputation - dressing change (Medical Encyclopedia) Also in Spanish Phantom limb pain (Medical Encyclopedia) Also in Spanish Traumatic amputation (Medical Encyclopedia) Also in Spanish Topic Image MEDICAL ENCYCLOPEDIA Foot amputation - discharge Leg amputation - discharge Leg or foot amputation Leg or foot amputation - dressing change Phantom limb pain Traumatic amputation Related Health Topics Artificial Limbs Disclaimers MedlinePlus links to health information from the National Institutes of Health and other federal government agencies. MedlinePlus also links to health information from non-government Web sites. See our disclaimer about external links and our quality guidelines .",
  "source": "MedlinePlus",
  "url": "https://medlineplus.gov/limbloss.html",
  "category": "health_topic",
  "language": "en",
  "fetched_at": "2026-04-24T07:31:00.393698+00:00"
}