{
  "id": 1847,
  "title": "G6PD Deficiency: MedlinePlus",
  "content": "G6PD Deficiency Also called: Glucose-6-phosphate dehydrogenase deficiency Summary Glucose-6-phosphate dehydrogenase (G6PD) deficiency is a genetic disorder that is most common in males. About 1 in 10 African American males in the United States has it. G6PD deficiency mainly affects red blood cells , which carry oxygen from the lungs to tissues throughout the body. The most common medical problem it can cause is hemolytic anemia . That happens when red blood cells are destroyed faster than the body can replace them. If you have G6PD deficiency, you may not have symptoms. Symptoms happen if your red blood cells are exposed to certain chemicals in food or medicine, certain bacterial or viral infections, or stress. They may include: Paleness Jaundice Dark urine Fatigue Shortness of breath Enlarged spleen Rapid heart rate A blood test can tell if you have it. Treatments include medicines to treat infection, avoiding substances that cause the problem with red blood cells, and sometimes transfusions. NIH: National Library of Medicine Learn More Anemia, Nonspherocytic Hemolytic, Due to G6PD Deficiency (Genetic and Rare Diseases Information Center) Blood Count Tests: MedlinePlus Health Topic (National Library of Medicine) Also in Spanish G6PD Deficiency (For Parents) (Nemours Foundation) Also in Spanish G6PD Test (National Library of Medicine) Also in Spanish Glucose-6-phosphate dehydrogenase deficiency (Medical Encyclopedia) Also in Spanish Genetics Glucose-6-phosphate dehydrogenase deficiency: MedlinePlus Genetics (National Library of Medicine) Clinical Trials ClinicalTrials.gov: Glucosephosphate Dehydrogenase Deficiency (National Institutes of Health) Journal Articles References and abstracts from MEDLINE/PubMed (National Library of Medicine) Article: The research progress on the role of glucose-6-phosphate dehydrogenase in immune... Article: Performance evaluation of an automated method for accurate identification of glucose-6-phosphate... Article: Pooled prevalence of Glucose-6-phosphate dehydrogenase deficiency among malaria patients in Ethiopia:... G6PD Deficiency -- see more articles Patient Handouts Glucose-6-phosphate dehydrogenase (Medical Encyclopedia) Also in Spanish Topic Image Disclaimers MedlinePlus links to health information from the National Institutes of Health and other federal government agencies. MedlinePlus also links to health information from non-government Web sites. See our disclaimer about external links and our quality guidelines .",
  "source": "MedlinePlus",
  "url": "https://medlineplus.gov/g6pddeficiency.html",
  "category": "health_topic",
  "language": "en",
  "fetched_at": "2026-04-24T07:50:17.432511+00:00"
}