{
  "id": 683,
  "title": "Endocrine System: MedlinePlus",
  "content": "Endocrine System See all Endocrine System topics Select One: Adrenal Gland Ovary Pancreas Pituitary Gland Testicles Thyroid Gland The Adrenal Glands Addison Disease Adrenal Gland Cancer Adrenal Gland Disorders Endocrine Diseases Hormones Pheochromocytoma The Ovaries Endocrine Diseases Hormones Menstruation Ovarian Cancer Ovarian Cysts Polycystic Ovary Syndrome Primary Ovarian Insufficiency The Pancreas Diabetes Diabetes Complications Diabetes in Children and Teens Diabetes Type 1 Diabetes Type 2 Endocrine Diseases Hormones How to Prevent Diabetes Islet Cell Transplantation Pancreas Transplantation Pancreatic Cancer Pancreatic Diseases Prediabetes The Pituitary Gland Diabetes Insipidus Dwarfism Endocrine Diseases Growth Disorders Hormones Pituitary Disorders Pituitary Tumors The Testicles Endocrine Diseases Hormones Testicular Cancer Testicular Disorders The Thyroid Gland Endocrine Diseases Hormones Hyperthyroidism Hypothyroidism Parathyroid Disorders Thyroid Cancer Thyroid Diseases Thyroid Tests",
  "source": "MedlinePlus",
  "url": "https://medlineplus.gov/endocrinesystem.html",
  "category": "health_topic",
  "language": "en",
  "fetched_at": "2026-04-24T06:30:06.378693+00:00",
  "reason": "duplicate_url"
}