{
  "id": 692,
  "title": "Los Institutos Nacionales de Salud |",
  "content": "Contenido destacado Problemas en los tendones Controlando la gastroparesia ¿Qué es la diabetes? El estilo de dieta DASH ayuda a controlar el nivel de azúcar en la sangre Temas de salud Temas de salud A–Z Cáncer Drogas, alcohol y tabaco Grupos demográficos Salud mental Salud y bienestar",
  "source": "NIH",
  "url": "https://salud.nih.gov/",
  "category": "health_guideline",
  "language": "en",
  "fetched_at": "2026-04-24T06:36:08.045137+00:00",
  "reason": "content_too_short"
}