{
  "id": 693,
  "title": "Problemas comunes de los reci횄짤n nacidos: MedlinePlus en espa횄짹ol",
  "content": "Problemas comunes de los reci횄짤n nacidos Otros nombres: Enfermedades comunes de los reci횄짤n nacidos, Enfermedades comunes en los beb횄짤s, Problemas comunes de salud de los beb횄짤s Introducci횄쨀n Es un momento dif횄짯cil cuando su beb횄짤 est횄징 enfermo. Los problemas de salud m횄징s comunes en los beb횄짤s incluyen resfr횄짯os, tos, fiebre y v횄쨀mitos. Los bebes tambi횄짤n puede tener problemas de piel, como sarpullido del pa횄짹al o costra l횄징ctea . Muchos de estos problemas no son serios. Es importante saber c횄쨀mo ayudar a su beb횄짤 enfermo y c횄쨀mo reconocer las se횄짹ales de aviso de problemas m횄징s serios. Conf횄짯e en su intuici횄쨀n. Si est횄징 preocupada por su beb횄짤, llame inmediatamente a un profesional de la salud. Comience aqu횄짯 Afecciones comunes de los reci횄짤n nacidos (Academia Americana de Pediatr횄짯a) Tambi횄짤n en ingl횄짤s 횂쩔Cu횄징les son algunos de los aspectos b횄징sicos de la salud infantil? (Instituto Nacional de Salud Infantil y Desarrollo Humano) Tambi횄짤n en ingl횄짤s Diagn횄쨀stico y ex횄징menes Fiebre (temperatura alta) en ni횄짹os (para padres) (Fundaci횄쨀n Nemours) Tambi횄짤n en ingl횄짤s Tratamientos y terapias Cu횄징ndo dar medicina para la tos y el resfriado a los ni횄짹os (Administraci횄쨀n de Alimentos y Medicamentos) Tambi횄짤n en ingl횄짤s Obstrucci횄쨀n del conducto lagrimal: Masajes en el conducto lagrimal (para padres) (Fundaci횄쨀n Nemours) Tambi횄짤n en ingl횄짤s Tratamiento de las obstrucciones del conducto lagrimal con una sonda (para padres) (Fundaci횄쨀n Nemours) Tambi횄짤n en ingl횄짤s Tratamiento del v횄쨀mito (Academia Americana de Pediatr횄짯a) Tambi횄짤n en ingl횄짤s Asuntos relacionados Alivie el dolor de la dentici횄쨀n de los beb횄짤s y los ni횄짹os de una manera segura (Administraci횄쨀n de Alimentos y Medicamentos) Tambi횄짤n en ingl횄짤s C횄쨀mo aprovechar al m횄징ximo una visita al m횄짤dico (para padres) (Fundaci횄쨀n Nemours) Tambi횄짤n en ingl횄짤s Elegir a un pediatra para su beb횄짤 reci횄짤n nacido (Fundaci횄쨀n Nemours) Tambi횄짤n en ingl횄짤s 횂쩔Su beb횄짤 est횄징 enfermo? Cu횄징ndo solicitar atenci횄쨀n m횄짤dica (Fundaci횄쨀n Mayo para la Educaci횄쨀n y la Investigaci횄쨀n M횄짤dica) Tambi횄짤n en ingl횄짤s Asuntos espec횄짯ficos Acn횄짤 del beb횄짤 (Fundaci횄쨀n Mayo para la Educaci횄쨀n y la Investigaci횄쨀n M횄짤dica) Tambi횄짤n en ingl횄짤s C횄쨀licos (Fundaci횄쨀n Nemours) Tambi횄짤n en ingl횄짤s Cuidados personales para el llanto y los c횄쨀licos (Enciclopedia M횄짤dica) Tambi횄짤n en ingl횄짤s Cuidados personales para la regurgitaci횄쨀n (Enciclopedia M횄짤dica) Tambi횄짤n en ingl횄짤s Dentici횄쨀n (Enciclopedia M횄짤dica) Tambi횄짤n en ingl횄짤s Dermatitis del pa횄짹al (Fundaci횄쨀n Nemours) Tambi횄짤n en ingl횄짤s Dermatitis del pa횄짹al (Enciclopedia M횄짤dica) Tambi횄짤n en ingl횄짤s Dermatitis seborreica (Enciclopedia M횄짤dica) Tambi횄짤n en ingl횄짤s Diarrea en beb횄짤s (Enciclopedia M횄짤dica) Tambi횄짤n en ingl횄짤s Di횄징stasis de rectos (Enciclopedia M횄짤dica) Tambi횄짤n en ingl횄짤s Efectos hormonales en los reci횄짤n nacidos (Enciclopedia M횄짤dica) Tambi횄짤n en ingl횄짤s Eritema t횄쨀xico (Enciclopedia M횄짤dica) Tambi횄짤n en ingl횄짤s Erupci횄쨀n en ni횄짹os menores de 2 a횄짹os (Enciclopedia M횄짤dica) Tambi횄짤n en ingl횄짤s Fiebre sin temor (Academia Americana de Pediatr횄짯a) Fosita o papiloma preauricular (Enciclopedia M횄짤dica) Tambi횄짤n en ingl횄짤s Gripe y su beb횄짤 (Enciclopedia M횄짤dica) Tambi횄짤n en ingl횄짤s Ictericia en reci횄짤n nacidos sanos (Fundaci횄쨀n Nemours) Tambi횄짤n en ingl횄짤s Llanto excesivo en beb횄짤s (Enciclopedia M횄짤dica) Tambi횄짤n en ingl횄짤s Llanto y c횄쨀lico (Academia Americana de Pediatr횄짯a) Tambi횄짤n en ingl횄짤s Melanocitosis d횄짤rmica (Enciclopedia M횄짤dica) Tambi횄짤n en ingl횄짤s Milios (Enciclopedia M횄짤dica) Tambi횄짤n en ingl횄짤s Muguet (candidiasis oral) (Fundaci횄쨀n Nemours) Tambi횄짤n en ingl횄짤s Ni횄짹o irritable o melindroso (Enciclopedia M횄짤dica) Tambi횄짤n en ingl횄짤s Perlas de Epstein (Enciclopedia M횄짤dica) Tambi횄짤n en ingl횄짤s Reflujo gastroesof횄징gico en beb횄짤s (Enciclopedia M횄짤dica) Tambi횄짤n en ingl횄짤s Resfr횄짯o com횄쨘n en beb횄짤s (Fundaci횄쨀n Mayo para la Educaci횄쨀n y la Investigaci횄쨀n M횄짤dica) Tambi횄짤n en ingl횄짤s Sarpullidos del beb횄짤: Eczema o eccema (Academia Americana de Pediatr횄짯a) Signos en la piel de los reci횄짤n nacidos (Enciclopedia M횄짤dica) Tambi횄짤n en ingl횄짤s S횄짯ndrome de cabeza plana (plagiocefalia posicional) (Fundaci횄쨀n Nemours) Tambi횄짤n en ingl횄짤s Tos (para padres) (Fundaci횄쨀n Nemours) Tambi횄짤n en ingl횄짤s Vista de su hijo (Fundaci횄쨀n Nemours) Tambi횄짤n en ingl횄짤s V횄쨀mitos (para padres) (Fundaci횄쨀n Nemours) Tambi횄짤n en ingl횄짤s Im횄징genes Serie de la exanguinotransfusi횄쨀n (Enciclopedia M횄짤dica) Tambi횄짤n en ingl횄짤s Especialistas Encuentre un pediatra o un pediatra especialista (Academia Americana de Pediatr횄짯a) Tambi횄짤n en ingl횄짤s Tema Imagen Temas de salud relacionados Beb횄짤 prematuro Chequeo m횄짤dico del beb횄짤 Cuidado del reci횄짤n nacido y del beb횄짤 Desarrollo del beb횄짤 y del reci횄짤n nacido Nutrici횄쨀n del beb횄짤 y del reci횄짤n nacido Problemas poco comunes de los reci횄짤n nacidos Institutos Nacionales de la Salud El organismo de los NIH principalmente responsable por realizar investigaciones cient횄짯ficas sobre Problemas comunes de los reci횄짤n nacidos es el Instituto Nacional de Salud Infantil y Desarrollo Humano, Eunice Kennedy Shriver Exenciones MedlinePlus en espa횄짹ol contiene enlaces a documentos con informaci횄쨀n de salud de los Institutos Nacionales de la Salud y otras agencias del gobierno federal de los EE. UU. MedlinePlus en espa횄짹ol tambi횄짤n contiene enlaces a sitios web no gubernamentales. Visite nuestras cl횄징usulas de exenci횄쨀n de responsabilidad sobre enlaces externos y nuestros criterios de selecci횄쨀n .",
  "source": "MedlinePlus ES",
  "url": "https://medlineplus.gov/spanish/commoninfantandnewbornproblems.html",
  "category": "health_topic",
  "language": "es",
  "fetched_at": "2026-04-24T06:50:26.728361+00:00",
  "reason": "duplicate_url"
}