{
  "id": 693,
  "title": "Hidrocefalia | Agua en el cerebro | MedlinePlus en espa횄짹ol",
  "content": "Hidrocefalia Otros nombres: Agua en el cerebro En esta p횄징gina Ent횄짤rese Introducci횄쨀n Comience aqu횄짯 Diagn횄쨀stico y ex횄징menes Tratamientos y terapias Para saber m횄징s Viviendo con... Asuntos relacionados Asuntos espec횄짯ficos Para ver, jugar y aprender Im횄징genes Investigaciones Informaci횄쨀n no disponible Recursos Informaci횄쨀n no disponible Para usted Ni횄짹os/as Introducci횄쨀n La hidrocefalia es la acumulaci횄쨀n de una cantidad excesiva de l횄짯quido cefalorraqu횄짯deo en el cerebro. Normalmente, este fluido protege y amortigua el cerebro. Sin embargo, demasiado l횄짯quido ejerce una presi횄쨀n da횄짹ina para el cerebro. La hidrocefalia puede ser cong횄짤nita, que se presenta al nacer. Sus causas incluyen problemas gen횄짤ticos y problemas que se desarrollan en el feto durante el embarazo. El principal signo de la hidrocefalia cong횄짤nita es una cabeza con un tama횄짹o fuera de lo normal. La hidrocefalia tambi횄짤n puede presentarse despu횄짤s de nacer. Esto se llama hidrocefalia adquirida. Puede ocurrir a cualquier edad. Las causas pueden incluir traumatismos en la cabeza, derrames cerebrales, infecciones, tumores y hemorragia cerebral. Los s횄짯ntomas de la hidrocefalia pueden incluir: Dolor de cabeza V횄쨀mitos y n횄징usea Visi횄쨀n borrosa Problemas de equilibrio Problemas para controlar la vejiga Problemas con el pensamiento y la memoria La hidrocefalia puede causar da횄짹os permanentes en el cerebro y provocar problemas con el desarrollo f횄짯sico y mental. Cuando no se trata, suele ser mortal. Con tratamiento, muchas personas llevan una vida normal, con ciertas limitaciones. El tratamiento suele incluir una cirug횄짯a para implantar una derivaci횄쨀n. Una derivaci횄쨀n es un tubo flexible pero robusto. Este desv횄짯a el flujo del l횄짯quido cefalorraqu횄짯deo a otra zona del cuerpo donde pueda ser absorbido. Las medicinas y la rehabilitaci횄쨀n tambi횄짤n pueden ayudar. NIH: Instituto Nacional de Trastornos Neurol횄쨀gicos y Accidentes Cerebrovasculares Comience aqu횄짯 Entendiendo la hidrocefalia (Asociaci횄쨀n de Hidrocefalia) Hidrocefalia (Instituto Nacional de Trastornos Neurol횄쨀gicos y Accidentes Cerebrovasculares) Hidrocefalia (Enciclopedia M횄짤dica) Tambi횄짤n en ingl횄짤s Hidrocefalia (Fundaci횄쨀n Mayo para la Educaci횄쨀n y la Investigaci횄쨀n M횄짤dica) Tambi횄짤n en ingl횄짤s Diagn횄쨀stico y ex횄징menes Cisternograf횄짯a con radion횄쨘clidos (Enciclopedia M횄짤dica) Tambi횄짤n en ingl횄짤s Hidrocefalia: Diagn횄쨀stico y tratamiento (Fundaci횄쨀n Mayo para la Educaci횄쨀n y la Investigaci횄쨀n M횄짤dica) Recolecci횄쨀n de l횄짯quido cefalorraqu횄짯deo (LCR) (Enciclopedia M횄짤dica) Tambi횄짤n en ingl횄짤s RMN del cerebro (Colegio Americano de Radiolog횄짯a; Sociedad de Radiolog횄짯a de Norteam횄짤rica) Tambi횄짤n en ingl횄짤s TC de cabeza (Colegio Americano de Radiolog횄짯a; Sociedad de Radiolog횄짯a de Norteam횄짤rica) Tambi횄짤n en ingl횄짤s Transiluminaci횄쨀n (Enciclopedia M횄짤dica) Tambi횄짤n en ingl횄짤s Tratamientos y terapias Cirug횄짯a del cerebro (Enciclopedia M횄짤dica) Tambi횄짤n en ingl횄짤s Derivaci횄쨀n ventriculoperitoneal (Enciclopedia M횄짤dica) Tambi횄짤n en ingl횄짤s Viviendo con... Alta tras cirug횄짯a del cerebro (Enciclopedia M횄짤dica) Tambi횄짤n en ingl횄짤s Alta tras derivaci횄쨀n ventriculoperitoneal (Enciclopedia M횄짤dica) Tambi횄짤n en ingl횄짤s Asuntos relacionados Hernia cerebral (Enciclopedia M횄짤dica) Tambi횄짤n en ingl횄짤s Asuntos espec횄짯ficos Fontanelas abultadas (Enciclopedia M횄짤dica) Tambi횄짤n en ingl횄짤s Hidrocefalia normotensiva (Enciclopedia M횄짤dica) Tambi횄짤n en ingl횄짤s Im횄징genes Craneotom횄짯a (Enciclopedia M횄짤dica) Tambi횄짤n en ingl횄짤s Hidrocefalia (Enciclopedia M횄짤dica) Tambi횄짤n en ingl횄짤s Ni횄짹os/as Hidrocefalia (Fundaci횄쨀n Nemours) Tambi횄짤n en ingl횄짤s Tema Imagen Temas de salud relacionados Malformaciones de Chiari Malformaciones del cerebro Institutos Nacionales de la Salud El organismo de los NIH principalmente responsable por realizar investigaciones cient횄짯ficas sobre Hidrocefalia es el Instituto Nacional de Trastornos Neurol횄쨀gicos y Accidentes Cerebrovasculares Exenciones MedlinePlus en espa횄짹ol contiene enlaces a documentos con informaci횄쨀n de salud de los Institutos Nacionales de la Salud y otras agencias del gobierno federal de los EE. UU. MedlinePlus en espa횄짹ol tambi횄짤n contiene enlaces a sitios web no gubernamentales. Visite nuestras cl횄징usulas de exenci횄쨀n de responsabilidad sobre enlaces externos y nuestros criterios de selecci횄쨀n .",
  "source": "MedlinePlus ES",
  "url": "https://medlineplus.gov/spanish/hydrocephalus.html",
  "category": "health_topic",
  "language": "es",
  "fetched_at": "2026-04-24T06:48:49.871682+00:00",
  "reason": "duplicate_url"
}