{
  "id": 693,
  "title": "Enciclopedia m횄짤dica: U: MedlinePlus",
  "content": "Enciclopedia m횄짤dica: U 횄혳lcera p횄짤ptica 횄혳lceras 횄혳lceras bucales 횄혳lceras bucales 횄혳lceras de dec횄쨘bito - Qu횄짤 preguntarle al m횄짤dico 횄혳lceras e infecciones corneales 횄혳lceras en los pies por diabetes 횄혳lceras genitales en las mujeres 횄혳lceras genitales en los hombres Ultrasonido Ultrasonido Doppler transcraneal Ultrasonido intravascular card횄짯aco U횄짹a del pie encarnada Una gu횄짯a para ayudar a los ni횄짹os a entender el c횄징ncer Una gu횄짯a sobre las hierbas medicinales Ureterocele Ureteroscopia Uretritis Urocultivo Urocultivo - muestra por sondaje Uroflujometr횄짯a Uropat횄짯a obstructiva Urostom횄짯a - cuidado de la piel y del estoma Urticaria Urticaria pigmentosa Uso de guantes en el hospital Uso de inmovilizadores Uso de muletas Uso de sustancias - anfetaminas Uso de sustancias - coca횄짯na Uso de sustancias - fenciclidina Uso de sustancias - inhalantes Uso de sustancias - LSD Uso de sustancias - marihuana Uso de un bast횄쨀n Uso de un caminador Uso del espir횄쨀metro de incentivo Uso del hombro despu횄짤s de cirug횄짯a Uso del hombro despu횄짤s de la artroplastia Uso del ox횄짯geno en el hogar Uso del ox횄짯geno en el hogar - qu횄짤 preguntarle al m횄짤dico Uso prudente de los antibi횄쨀ticos Utensilios de cocina y nutrici횄쨀n 횄혳vea Uve횄짯tis Uvulitis Uvulopalatofaringoplastia (UPFP)",
  "source": "MedlinePlus ES",
  "url": "https://medlineplus.gov/spanish/ency/encyclopedia_U.htm",
  "category": "health_topic",
  "language": "es",
  "fetched_at": "2026-04-24T06:42:56.811049+00:00",
  "reason": "duplicate_url"
}