{
  "id": 465,
  "title": "Seguridad al conducir: MedlinePlus en espa횄짹ol",
  "content": "Seguridad al conducir Otros nombres: Seguridad en el auto, Seguridad en los veh횄짯culos de motor En esta p횄징gina Ent횄짤rese Introducci횄쨀n Comience aqu횄짯 Para saber m횄징s Asuntos relacionados Para ver, jugar y aprender Informaci횄쨀n no disponible Investigaciones Informaci횄쨀n no disponible Recursos Informaci횄쨀n no disponible Para usted Ni횄짹os/as Adolescentes Personas mayores Introducci횄쨀n Cada a횄짹o miles de personas en Estados Unidos muere en un accidente automovil횄짯stico. Tratar de prevenir estos accidentes es una parte de la seguridad al conducir. 횄혟stas son algunas cosas que puede hacer para estar m횄징s seguro en las carreteras y caminos: Aseg횄쨘rese de que el veh횄짯culo es seguro y funciona correctamente Utilice asientos de seguridad para los ni횄짹os Use el cintur횄쨀n de seguridad No conduzca demasiado r횄징pido o agresivamente No conduzca si no est횄징 en condiciones de hacerlo Seguridad tambi횄짤n significa estar pendiente de otros. Comparta la calle con bicicletas y motos y preste atenci횄쨀n a los peatones. Comience aqu횄짯 Conducci횄쨀n segura: Protegerse detr횄징s del volante (Institutos Nacionales de la Salud) Tambi횄짤n en ingl횄짤s Asuntos relacionados Seguridad de las llantas: Todo rueda sobre ellas (Administraci횄쨀n Nacional de Seguridad del Tr횄징fico en las Carreteras) Ni횄짹os/as 횂쩔C횄쨀mo se puede promover la seguridad de los ni횄짹os en un coche? (Instituto Nacional de Salud Infantil y Desarrollo Humano) Golpe de calor y veh횄짯culos calientes (Colegio Americano de M횄짤dicos de Emergencia) Tambi횄짤n en ingl횄짤s Mantener a los ni횄짹os seguros ante los peligros de los autos calientes (Fundaci횄쨀n Nemours) Tambi횄짤n en ingl횄짤s Seguridad con las bolsas de aire (para padres) (Fundaci횄쨀n Nemours) Tambi횄짤n en ingl횄짤s Seguridad en el autom횄쨀vil (Fundaci횄쨀n Nemours) Tambi횄짤n en ingl횄짤s Sillas de seguridad para ni횄짹os (Enciclopedia M횄짤dica) Tambi횄짤n en ingl횄짤s Adolescentes Evite que su hijo adolescente est횄짤 distra횄짯do al volante (Institutos Nacionales de la Salud) Personas mayores Conducci횄쨀n y los adultos mayores (Enciclopedia M횄짤dica) Tambi횄짤n en ingl횄짤s Conductores de la tercera edad (Instituto Nacional sobre el Envejecimiento) Tambi횄짤n en ingl횄짤s Tema Imagen Temas de salud relacionados Inhabilidad para conducir Exenciones MedlinePlus en espa횄짹ol contiene enlaces a documentos con informaci횄쨀n de salud de los Institutos Nacionales de la Salud y otras agencias del gobierno federal de los EE. UU. MedlinePlus en espa횄짹ol tambi횄짤n contiene enlaces a sitios web no gubernamentales. Visite nuestras cl횄징usulas de exenci횄쨀n de responsabilidad sobre enlaces externos y nuestros criterios de selecci횄쨀n .",
  "source": "MedlinePlus ES",
  "url": "https://medlineplus.gov/spanish/motorvehiclesafety.html",
  "category": "health_topic",
  "language": "es",
  "fetched_at": "2026-04-20T19:05:06.741186+00:00"
}