{
  "id": 972,
  "title": "Fibrosis qu횄짯stica: MedlinePlus en espa횄짹ol",
  "content": "Fibrosis qu횄짯stica En esta p횄징gina Ent횄짤rese Introducci횄쨀n Comience aqu횄짯 Diagn횄쨀stico y ex횄징menes Para saber m횄징s Viviendo con... Asuntos relacionados Para ver, jugar y aprender Informaci횄쨀n no disponible Investigaciones Estad횄짯sticas e investigaci횄쨀n Recursos Especialistas Para usted Ni횄짹os/as Adolescentes Introducci횄쨀n La fibrosis qu횄짯stica es una enfermedad hereditaria de las gl횄징ndulas mucosas y sudor횄짯paras. Afecta principalmente los pulmones, el p횄징ncreas, el h횄짯gado, los intestinos, los senos paranasales y los 횄쨀rganos sexuales. La fibrosis qu횄짯stica hace que la mucosidad sea espesa y pegajosa. Esta mucosidad tapa los pulmones, causando problemas para respirar y facilitando el crecimiento de bacterias. Esto puede provocar infecciones pulmonares repetidas y da횄짹os pulmonares. Los s횄짯ntomas y la severidad de la fibrosis qu횄짯stica pueden variar. Algunas personas tienen problemas serios desde el nacimiento. Otras pueden tener un tipo m횄징s leve de la enfermedad que no se manifiesta hasta la adolescencia o al inicio de la edad adulta. A veces se tienen pocos s횄짯ntomas, pero m횄징s tarde es posible tener m횄징s. La fibrosis qu횄짯stica se diagnostica a trav횄짤s de varias pruebas, tales como genes, sangre y pruebas de sudor. No existe cura, pero los tratamientos han mejorado mucho en los 횄쨘ltimos a횄짹os. En el pasado, la mayor횄짯a de las muertes por fibrosis qu횄짯stica eran ni횄짹os y adolescentes. Hoy en d횄짯a, con la mejora de los tratamientos, algunas personas con fibrosis qu횄짯stica viven pasados los cuarenta, cincuenta a횄짹os o m횄징s. Los tratamientos pueden incluir terapia f횄짯sica para el pecho, terapias nutricionales y respiratorias , medicinas y ejercicio. NIH: Instituto Nacional del Coraz횄쨀n, los Pulmones y la Sangre Comience aqu횄짯 Fibrosis qu횄짯stica (Enciclopedia M횄짤dica) Tambi횄짤n en ingl횄짤s Fibrosis qu횄짯stica (Fundaci횄쨀n de Ni횄짹os con Defectos de Nacimiento March of Dimes) Fibrosis qu횄짯stica (Centro de Informaci횄쨀n sobre Enfermedades Gen횄짤ticas y Raras) Fibrosis qu횄짯stica (para padres) (Fundaci횄쨀n Nemours) Tambi횄짤n en ingl횄짤s 횂쩔Qu횄짤 es la fibrosis qu횄짯stica? (Instituto Nacional del Coraz횄쨀n, los Pulmones y la Sangre) Tambi횄짤n en ingl횄짤s Diagn횄쨀stico y ex횄징menes Cribado respiratorio para la fibrosis qu횄짯stica: Esputo (Fundaci횄쨀n Nemours) Tambi횄짤n en ingl횄짤s Elastasa fecal (Biblioteca Nacional de Medicina) Tambi횄짤n en ingl횄짤s Examen de estimulaci횄쨀n de secretina (Enciclopedia M횄짤dica) Tambi횄짤n en ingl횄짤s Examen de tripsin횄쨀geno (Enciclopedia M횄짤dica) Tambi횄짤n en ingl횄짤s Fibrosis qu횄짯stica: An횄징lisis de cloruro en el sudor (Fundaci횄쨀n Nemours) Grasa fecal (Enciclopedia M횄짤dica) Tambi횄짤n en ingl횄짤s Prueba de detecci횄쨀n para fibrosis qu횄짯stica neonatal (Enciclopedia M횄짤dica) Tambi횄짤n en ingl횄짤s Prueba de electrolitos en el sudor (Enciclopedia M횄짤dica) Tambi횄짤n en ingl횄짤s Prueba de portador de fibrosis qu횄짯stica (Fundaci횄쨀n de Ni횄짹os con Defectos de Nacimiento March of Dimes) Tambi횄짤n en ingl횄짤s Prueba de sudor (Biblioteca Nacional de Medicina) Tambi횄짤n en ingl횄짤s Quimotripsina en heces (Biblioteca Nacional de Medicina) Tambi횄짤n en ingl횄짤s Tripsina y quimotripsina en las heces (Enciclopedia M횄짤dica) Tambi횄짤n en ingl횄짤s Viviendo con... Consejos diet횄짤ticos para ni횄짹os con fibrosis qu횄짯stica (Fundaci횄쨀n Nemours) Tambi횄짤n en ingl횄짤s Consideraciones nutricionales para la fibrosis qu횄짯stica (Enciclopedia M횄짤dica) Tambi횄짤n en ingl횄짤s Drenaje postural (Enciclopedia M횄짤dica) Tambi횄짤n en ingl횄짤s Rehabilitaci횄쨀n pulmonar: Tema de salud de MedlinePlus (Biblioteca Nacional de Medicina) Tambi횄짤n en ingl횄짤s Viajar con problemas respiratorios (Enciclopedia M횄짤dica) Tambi횄짤n en ingl횄짤s Asuntos relacionados Maravillas de la mucosidad y la flema (Institutos Nacionales de la Salud) Tambi횄짤n en ingl횄짤s 횂쩔Qu횄짤 es la bronquiectasia? (Instituto Nacional del Coraz횄쨀n, los Pulmones y la Sangre) Tambi횄짤n en ingl횄짤s Uso del ox횄짯geno en el hogar (Enciclopedia M횄짤dica) Tambi횄짤n en ingl횄짤s Uso del ox횄짯geno en el hogar: Qu횄짤 preguntarle al m횄짤dico (Enciclopedia M횄짤dica) Tambi횄짤n en ingl횄짤s Estad횄짯sticas e investigaci횄쨀n Investigaci횄쨀n acerca de la fibrosis qu횄짯stica (Instituto Nacional del Coraz횄쨀n, los Pulmones y la Sangre) Tambi횄짤n en ingl횄짤s Especialistas Fundaci횄쨀n de Ni횄짹os con Defectos de Nacimiento / March of Dimes (Fundaci횄쨀n de Ni횄짹os con Defectos de Nacimiento March of Dimes) Tambi횄짤n en ingl횄짤s Ni횄짹os/as Fibrosis qu횄짯stica (Academia Americana de Pediatr횄짯a) Adolescentes Consejos diet횄짤ticos para adolescentes con fibrosis qu횄짯stica (Fundaci횄쨀n Nemours) Tambi횄짤n en ingl횄짤s Tema Imagen Temas de salud relacionados Rehabilitaci횄쨀n pulmonar Terapia con ox횄짯geno Trasplante de pulm횄쨀n Institutos Nacionales de la Salud El organismo de los NIH principalmente responsable por realizar investigaciones cient횄짯ficas sobre Fibrosis qu횄짯stica es el Instituto Nacional del Coraz횄쨀n, los Pulmones y la Sangre Exenciones MedlinePlus en espa횄짹ol contiene enlaces a documentos con informaci횄쨀n de salud de los Institutos Nacionales de la Salud y otras agencias del gobierno federal de los EE. UU. MedlinePlus en espa횄짹ol tambi횄짤n contiene enlaces a sitios web no gubernamentales. Visite nuestras cl횄징usulas de exenci횄쨀n de responsabilidad sobre enlaces externos y nuestros criterios de selecci횄쨀n .",
  "source": "MedlinePlus ES",
  "url": "https://medlineplus.gov/spanish/cysticfibrosis.html",
  "category": "health_topic",
  "language": "es",
  "fetched_at": "2026-04-24T07:09:20.558736+00:00"
}