{
  "id": 361,
  "title": "Trastornos del espectro alcoh횄쨀lico fetal: MedlinePlus en espa횄짹ol",
  "content": "Trastornos del espectro alcoh횄쨀lico fetal Otros nombres: TEAF En esta p횄징gina Ent횄짤rese Introducci횄쨀n Comience aqu횄짯 S횄짯ntomas Diagn횄쨀stico y ex횄징menes Prevenci횄쨀n y factores de riesgo Para saber m횄징s Asuntos relacionados Para ver, jugar y aprender Informaci횄쨀n no disponible Investigaciones Informaci횄쨀n no disponible Recursos Especialistas Para usted Informaci횄쨀n no disponible Introducci횄쨀n El alcohol puede da횄짹ar a su beb횄짤 en cualquier etapa del embarazo. Esto incluye los primeros meses, antes de que usted sepa que est횄징 embarazada. Tomar alcohol durante el embarazo puede causar un grupo de afecciones llamadas trastornos del espectro alcoh횄쨀lico fetal. Los ni횄짹os que nacen con estos trastornos pueden mostrar una serie de problemas, incluyendo m횄짤dicos, conductuales, educativos y sociales. Los tipos de problemas que tengan dependen del tipo de trastorno que tengan. Estos pueden incluir: Rasgos faciales anormales, como un surco liso entre la nariz y el labio superior Tama횄짹o de cabeza peque횄짹o Menor altura que el promedio Bajo peso corporal Mala coordinaci횄쨀n Comportamiento hiperactivo Dificultad con la atenci횄쨀n y la memoria Problemas de aprendizaje y dificultad en la escuela Retrasos en el habla y el lenguaje Discapacidad intelectual o bajo coeficiente intelectual Pobre razonamiento y capacidad de juicio Problemas de sue횄짹o y succi횄쨀n del beb횄짤 Problemas de visi횄쨀n o audici횄쨀n Problemas con el coraz횄쨀n, los ri횄짹ones o los huesos El s횄짯ndrome alcoh횄쨀lico fetal es el tipo de trastorno m횄징s serio. Las personas con este s횄짯ndrome sufren de anormalidades faciales que incluyen ojos muy separados y estrechos, problemas de crecimiento y anomal횄짯as del sistema nervioso. Diagnosticar el trastorno del espectro alcoh횄쨀lico fetal puede ser dif횄짯cil porque no hay una prueba m횄짤dica espec횄짯fica para ello, como un examen de sangre. El profesional de la salud har횄징 un diagn횄쨀stico al observar los signos y s횄짯ntomas del ni횄짹o , y preguntar횄징 si la madre bebi횄쨀 alcohol durante el embarazo. El trastorno del espectro alcoh횄쨀lico fetal dura toda la vida. No existe una cura, pero el tratamiento puede ayudar. Estos incluyen medicamentos para ayudar con algunos s횄짯ntomas, atenci횄쨀n m횄짤dica para problemas de salud, terapia de comportamiento y educacional, y capacitaci횄쨀n para padres. Un buen plan de tratamiento es espec횄짯fico para los problemas del ni횄짹o. Debe incluir un monitoreo cercano, seguimientos y cambios cuando sea necesario. Ciertos \"factores de protecci횄쨀n\" pueden ayudar a reducir los efectos del trastorno de espectro alcoh횄쨀lico fetal y ayudar quienes que los tienen a alcanzar todo su potencial. Estos incluyen: Un diagn횄쨀stico antes de los seis a횄짹os de edad Un ambiente en el amoroso, enriquecedor y estable durante los a횄짹os escolares La ausencia de violencia a su alrededor Participaci횄쨀n en educaci횄쨀n especial y servicios sociales No se conoce una cantidad segura de alcohol durante el embarazo. Para prevenir los trastornos, no debe beber alcohol mientras est횄징 embarazada o cuando pueda quedar embarazada. Centros para el Control y la Prevenci횄쨀n de Enfermedades Comience aqu횄짯 S횄짯ndrome de alcoholismo fetal (Enciclopedia M횄짤dica) Tambi횄짤n en ingl횄짤s Trastornos del espectro alcoh횄쨀lico fetal (Instituto Nacional sobre el Abuso de Alcohol y Alcoholismo) Tambi횄짤n en ingl횄짤s S횄짯ntomas S횄짯ndrome alcoh횄쨀lico fetal: S횄짯ntomas y causas (Fundaci횄쨀n Mayo para la Educaci횄쨀n y la Investigaci횄쨀n M횄짤dica) Diagn횄쨀stico y ex횄징menes Evaluaci횄쨀n de trastornos del espectro alcoh횄쨀lico fetal (TEAF) (Biblioteca Nacional de Medicina) Tambi횄짤n en ingl횄짤s S횄짯ndrome alcoh횄쨀lico fetal: Diagn횄쨀stico y tratamientos (Fundaci횄쨀n Mayo para la Educaci횄쨀n y la Investigaci횄쨀n M횄짤dica) Prevenci횄쨀n y factores de riesgo Alcohol durante el embarazo (Fundaci횄쨀n de Ni횄짹os con Defectos de Nacimiento March of Dimes) Tambi횄짤n en ingl횄짤s Alcohol y el embarazo (Organizaci횄쨀n de Especialistas de Informaci횄쨀n Teratol횄쨀gica) - PDF Alcohol y su embarazo (Instituto Nacional sobre el Abuso de Alcohol y Alcoholismo) Asuntos relacionados Ni횄짹os adoptados y en hogares de acogida con trastornos del espectro alcoh횄쨀lico fetal (Academia Americana de Pediatr횄짯a) Especialistas Findtreatment.gov en espa횄짹ol (Administraci횄쨀n de Servicios de la Salud Mental y Abuso de Sustancias) Tambi횄짤n en ingl횄짤s Fundaci횄쨀n de Ni횄짹os con Defectos de Nacimiento / March of Dimes (Fundaci횄쨀n de Ni횄짹os con Defectos de Nacimiento March of Dimes) Tambi횄짤n en ingl횄짤s Tema Imagen Temas de salud relacionados Trastorno por consumo de alcohol Institutos Nacionales de la Salud El organismo de los NIH principalmente responsable por realizar investigaciones cient횄짯ficas sobre Trastornos del espectro alcoh횄쨀lico fetal es el Instituto Nacional sobre el Abuso del Alcohol y Alcoholismo Exenciones MedlinePlus en espa횄짹ol contiene enlaces a documentos con informaci횄쨀n de salud de los Institutos Nacionales de la Salud y otras agencias del gobierno federal de los EE. UU. MedlinePlus en espa횄짹ol tambi횄짤n contiene enlaces a sitios web no gubernamentales. Visite nuestras cl횄징usulas de exenci횄쨀n de responsabilidad sobre enlaces externos y nuestros criterios de selecci횄쨀n .",
  "source": "MedlinePlus ES",
  "url": "https://medlineplus.gov/spanish/fetalalcoholspectrumdisorders.html",
  "category": "health_topic",
  "language": "es",
  "fetched_at": "2026-04-20T19:01:26.893643+00:00"
}